README.md
setup.cfg
setup.py
cupy_chol.egg-info/PKG-INFO
cupy_chol.egg-info/SOURCES.txt
cupy_chol.egg-info/dependency_links.txt
cupy_chol.egg-info/not-zip-safe
cupy_chol.egg-info/requires.txt
cupy_chol.egg-info/top_level.txt
cupychol/__init__.py
cupychol/cupy_chol.cpp
cupychol/wrapper.py