Metadata-Version: 2.1
Name: cupy-chol
Version: 0.1.4
Summary: cupychol: Solve linear systems using Cholesky decomposition with CuPy arrays on GPU.
Home-page: https://github.com/ahnobari/CupyChol
Author: Amin Heyrani Nobari
Author-email: ahnobari@mit.edu
Classifier: Programming Language :: Python :: 3
Classifier: License :: OSI Approved :: MIT License
Classifier: Operating System :: OS Independent
Requires-Python: >=3.10
Requires-Dist: pybind11>=2.5.0
Requires-Dist: cupy>=8.0.0
Requires-Dist: numpy>=1.18.0
Requires-Dist: scipy>=1.4.0
Provides-Extra: dev
Requires-Dist: check-manifest; extra == "dev"
Requires-Dist: flake8; extra == "dev"
Requires-Dist: pytest; extra == "dev"
